cdiam_cli/__init__.py
cdiam_cli/__main__.py
cdiam_cli/api/__init__.py
cdiam_cli/api/api_action.py
cdiam_cli/api/download.py
cdiam_cli/api/settings.py
cdiam_cli/api/utils.py
cdiam_cli/command/__init__.py
cdiam_cli/command/data.py
cdiam_cli/command/project.py
cdiam_cli/helper/__init__.py
cdiam_cli/helper/curl_helper.py
cdiam_cli/helper/json_helper.py
cdiam_cli/helper/yaml_helper.py
cdiam_cli/main.py
cdiam_cli/schemas/__init__.py
cdiam_cli/schemas/analysis.py
cdiam_cli/schemas/base.py
cdiam_cli/schemas/project.py
cdiam_cli/schemas/schemas.py
cdiam_cli-0.1.10.dist-info/LICENSE.md
cdiam_cli-0.1.10.dist-info/METADATA
cdiam_cli-0.1.10.dist-info/WHEEL
cdiam_cli-0.1.10.dist-info/entry_points.txt
cdiam_cli-0.1.10.dist-info/RECORD
