Metadata-Version: 2.3
Name: cdiam-cli
Version: 0.1.10
Summary: 
Author: tungtp99
Author-email: tungtp181199@gmail.com
Requires-Python: >=3.9,<4.0
Classifier: Programming Language :: Python :: 3
Classifier: Programming Language :: Python :: 3.9
Classifier: Programming Language :: Python :: 3.10
Classifier: Programming Language :: Python :: 3.11
Classifier: Programming Language :: Python :: 3.12
Classifier: Programming Language :: Python :: 3.13
Requires-Dist: boto3 (>=1.37.34,<2.0.0)
Requires-Dist: click (>=8.1.7,<9.0.0)
Requires-Dist: datetime (>=5.5,<6.0)
Requires-Dist: idna (==3.4)
Requires-Dist: pydantic (==1.10.2)
Requires-Dist: pyyaml (>=6.0.1,<7.0.0)
Requires-Dist: typing-extensions (==4.3.0)
